tfc/version.py
tfc/__init__.py
tfc/mtfc.py
tfc/py.typed
tfc/utfc.py
tfc/utils/MakePlot.py
tfc/utils/TFCUtils.py
tfc/utils/CeSolver.py
tfc/utils/tfc_types.py
tfc/utils/CMakeLists.txt
tfc/utils/BF_Py.py
tfc/utils/BF.pyi
tfc/utils/Html.py
tfc/utils/__init__.py
tfc/utils/PlotlyMakePlot.py
tfc/utils/BF.h
tfc/utils/MayaviMakePlot.py
tfc/utils/Latex.py
tfc/utils/BF_Py.cc
tfc/utils/BF.cc
tfc/utils/BF.cpython-314-darwin.so
tfc-1.3.2.dist-info/RECORD
tfc-1.3.2.dist-info/WHEEL
tfc-1.3.2.dist-info/top_level.txt
tfc-1.3.2.dist-info/METADATA
tfc-1.3.2.dist-info/licenses/LICENSE
