Metadata-Version: 2.4
Name: tfc
Version: 1.3.2
Summary: Theory of Functional Connections (TFC): A functional interpolation framework with applications in differential equations.
Home-page: https://github.com/leakec/tfc.git
Author: Carl Leake and Hunter Johnston
Author-email: leakec57@gmail.com
License: MIT
Classifier: Development Status :: 4 - Beta
Classifier: Natural Language :: English
Classifier: Programming Language :: C++
Classifier: Programming Language :: Python :: 3 :: Only
Classifier: Topic :: Scientific/Engineering
Classifier: Topic :: Education
Requires-Python: >=3.11
License-File: LICENSE
Requires-Dist: numpy>=2.1.0
Requires-Dist: jax>=0.6.0
Requires-Dist: jaxlib>=0.6.0
Requires-Dist: jaxtyping
Requires-Dist: annotated-types
Requires-Dist: matplotlib
Requires-Dist: colorama
Requires-Dist: graphviz
Requires-Dist: yattag
Requires-Dist: sympy
Dynamic: author
Dynamic: author-email
Dynamic: classifier
Dynamic: home-page
Dynamic: license
Dynamic: license-file
Dynamic: requires-dist
Dynamic: requires-python
Dynamic: summary
